MANIFEST.in
README.rst
setup.cfg
setup.py
docs/source/README.rst
docs/source/changelog.rst
docs/source/conf.py
docs/source/index.rst
docs/source/licence.rst
docs/source/overview.rst
docs/source/todo.rst
docs/source/.static/.hidden
src/sact/__init__.py
src/sact/__init__.pyc
src/sact.epoch.egg-info/PKG-INFO
src/sact.epoch.egg-info/SOURCES.txt
src/sact.epoch.egg-info/dependency_links.txt
src/sact.epoch.egg-info/entry_points.txt
src/sact.epoch.egg-info/namespace_packages.txt
src/sact.epoch.egg-info/not-zip-safe
src/sact.epoch.egg-info/requires.txt
src/sact.epoch.egg-info/top_level.txt
src/sact/epoch/__init__.py
src/sact/epoch/__init__.pyc
src/sact/epoch/clock.py
src/sact/epoch/clock.pyc
src/sact/epoch/interfaces.py
src/sact/epoch/interfaces.pyc
src/sact/epoch/manageableclock.zcml
src/sact/epoch/strptime.py
src/sact/epoch/strptime.pyc
src/sact/epoch/timezone.py
src/sact/epoch/timezone.pyc
src/sact/epoch/utils.py
src/sact/epoch/utils.pyc
src/sact/epoch/tests/README.rst
src/sact/epoch/tests/__init__.py
src/sact/epoch/tests/__init__.pyc
src/sact/epoch/tests/overview.rst
src/sact/epoch/tests/tests.pyc