Metadata-Version: 1.1
Name: sact.epoch
Version: 1.3.0
Summary: Time object subclassing datetime allowing diverting local clock mecanism
Home-page: http://github.com/securactive/sact.epoch
Author: SecurActive SA
Author-email: opensource@securactive.net
License: BSD License
Keywords: sact time timedelta
Platform: UNKNOWN
Classifier: Programming Language :: Python
Classifier: Topic :: Software Development :: Libraries :: Python Modules
Classifier: Development Status :: 5 - Production/Stable
Classifier: Intended Audience :: Developers
Classifier: License :: OSI Approved :: BSD License
Classifier: Topic :: Software Development
